rxcat/__init__.py
rxcat/_msg.py
rxcat/_rpc.py
rxcat/_transport.py
rxcat/_udp.py
rxcat/_ws.py
rxcat/filters.py
sb_rxcat-1.0.7.dist-info/license
sb_rxcat-1.0.7.dist-info/METADATA
sb_rxcat-1.0.7.dist-info/WHEEL
sb_rxcat-1.0.7.dist-info/RECORD
